Workbook

Sheet 🏠 Dashboard
A1: FINANCIAL RISK & PORTFOLIO STRESS-TESTING MODEL
A2: Advanced Excel Portfolio Analytics | Monte Carlo VaR | 5 Scenario Stress-Test | 20 Securities
A4: TOTAL PORTFOLIO VALUE | C4: PORTFOLIO P&L | E4: PORTFOLIO RETURN | G4: PARAMETRIC VaR (10D) | I4: WEIGHTED AVG BETA | K4: SHARPE RATIO | M4: NO. SECURITIES
A5: =$'📊 Raw Data'.F23 | C5: =$'📊 Raw Data'.F23-$'📊 Raw Data'.E23 | E5: =($'📊 Raw Data'.F23-$'📊 Raw Data'.E23)/$'📊 Raw Data'.E23 | G5: =$'📉 VaR Model'.B15 | I5: =$'📈 KPI Engine'.B9 | K5: =$'📈 KPI Engine'.B12 | M5: =$'📈 KPI Engine'.B10
A8: ▶ ASSET CLASS ALLOCATION | H8: ▶ STRESS-TEST DRAWDOWN SUMMARY
A9: Asset Class | B9: Current Value ($) | C9: Allocation (%) | D9: Avg Return | E9: Avg Volatility | F9: Risk/Return | H9: Scenario | I9: Portfolio Impact ($) | J9: % Drawdown | K9: Severity
A10: Equity | B10: =SUMIF('📊 Raw Data'!B3:B22,A10,'📊 Raw Data'!F3:F22) | C10: =B10/'📊 Raw Data'!F23 | D10: =AVERAGEIF('📊 Raw Data'!B3:B22,A10,'📊 Raw Data'!H3:H22) | E10: =AVERAGEIF('📊 Raw Data'!B3:B22,A10,'📊 Raw Data'!I3:I22) | F10: =D10/E10 | H10: Rate Hike | I10: ='🎯 Scenario Stress-Test'!F14 | J10: ='🎯 Scenario Stress-Test'!H14 | K10: ='🎯 Scenario Stress-Test'!I14
A11: Fixed Income | B11: =SUMIF('📊 Raw Data'!B3:B22,A11,'📊 Raw Data'!F3:F22) | C11: =B11/'📊 Raw Data'!F23 | D11: =AVERAGEIF('📊 Raw Data'!B3:B22,A11,'📊 Raw Data'!H3:H22) | E11: =AVERAGEIF('📊 Raw Data'!B3:B22,A11,'📊 Raw Data'!I3:I22) | F11: =D11/E11 | H11: Liquidity Crunch | I11: ='🎯 Scenario Stress-Test'!F15 | J11: ='🎯 Scenario Stress-Test'!H15 | K11: ='🎯 Scenario Stress-Test'!I15
A12: Commodity | B12: =SUMIF('📊 Raw Data'!B3:B22,A12,'📊 Raw Data'!F3:F22) | C12: =B12/'📊 Raw Data'!F23 | D12: =AVERAGEIF('📊 Raw Data'!B3:B22,A12,'📊 Raw Data'!H3:H22) | E12: =AVERAGEIF('📊 Raw Data'!B3:B22,A12,'📊 Raw Data'!I3:I22) | F12: =D12/E12 | H12: Equity Crash | I12: ='🎯 Scenario Stress-Test'!F16 | J12: ='🎯 Scenario Stress-Test'!H16 | K12: ='🎯 Scenario Stress-Test'!I16
A13: Real Estate | B13: =SUMIF('📊 Raw Data'!B3:B22,A13,'📊 Raw Data'!F3:F22) | C13: =B13/'📊 Raw Data'!F23 | D13: =AVERAGEIF('📊 Raw Data'!B3:B22,A13,'📊 Raw Data'!H3:H22) | E13: =AVERAGEIF('📊 Raw Data'!B3:B22,A13,'📊 Raw Data'!I3:I22) | F13: =D13/E13 | H13: Currency Deval. | I13: ='🎯 Scenario Stress-Test'!F17 | J13: ='🎯 Scenario Stress-Test'!H17 | K13: ='🎯 Scenario Stress-Test'!I17
A14: TOTAL | B14: ='📊 Raw Data'!F23 | C14: =SUM(C10:C13) | H14: Stagflation | I14: ='🎯 Scenario Stress-Test'!F18 | J14: ='🎯 Scenario Stress-Test'!H18 | K14: ='🎯 Scenario Stress-Test'!I18
A17: 📋 WORKBOOK NAVIGATION
A18: 📊 Raw Data | D18: 500+ data points across 20 securities. Edit blue cells to update inputs.
A19: 📈 KPI Engine | D19: Core KPIs: portfolio return, Sharpe ratio, weighted beta, asset class breakdown.
A20: 🎯 Scenario Stress-Test | D20: 5 macro shock scenarios with live P&L impact and severity classification.
A21: 📉 VaR Model | D21: Parametric VaR, CVaR, and 30-path Monte Carlo simulation with breach detection.
A22: 🔍 Assumptions | D22: Full documentation of all model inputs, sources, and conventions.

Sheet 📊 Raw Data
A1: PORTFOLIO RAW DATA — FINANCIAL RISK & STRESS-TESTING MODEL
A2: Security ID | B2: Asset Class | C2: Sector | D2: Market | E2: Initial Value ($) | F2: Current Value ($) | G2: Weight (%) | H2: Annualized Return (%) | I2: Volatility (%) | J2: Beta | K2: Correlation to SPX | L2: P/E Ratio | M2: Dividend Yield (%) | N2: 52W High | O2: 52W Low
A3: SEC-001 | B3: Equity | C3: Technology | D3: US | E3: 120000 | F3: 145200 | G3: =E3/SUM($E$3:$E$22) | H3: 0.21 | I3: 0.185 | J3: 1.32 | K3: 0.88 | L3: 28.4 | M3: 0.008 | N3: 152 | O3: 98
A4: SEC-002 | B4: Equity | C4: Healthcare | D4: US | E4: 80000 | F4: 87600 | G4: =E4/SUM($E$3:$E$22) | H4: 0.095 | I4: 0.142 | J4: 0.78 | K4: 0.71 | L4: 22.1 | M4: 0.014 | N4: 95 | O4: 72
A5: SEC-003 | B5: Fixed Income | C5: Government | D5: US | E5: 150000 | F5: 151500 | G5: =E5/SUM($E$3:$E$22) | H5: 0.01 | I5: 0.031 | J5: 0.12 | K5: 0.18 | L5: - | M5: 0.038 | N5: 155 | O5: 148
A6: SEC-004 | B6: Equity | C6: Financials | D6: US | E6: 90000 | F6: 99000 | G6: =E6/SUM($E$3:$E$22) | H6: 0.1 | I6: 0.168 | J6: 1.05 | K6: 0.82 | L6: 15.6 | M6: 0.021 | N6: 108 | O6: 82
A7: SEC-005 | B7: Commodity | C7: Energy | D7: Global | E7: 60000 | F7: 54000 | G7: =E7/SUM($E$3:$E$22) | H7: -0.1 | I7: 0.284 | J7: 0.65 | K7: 0.44 | L7: - | M7: - | N7: 72 | O7: 48
A8: SEC-006 | B8: Equity | C8: Consumer Disc | D8: US | E8: 70000 | F8: 78400 | G8: =E8/SUM($E$3:$E$22) | H8: 0.12 | I8: 0.192 | J8: 1.18 | K8: 0.79 | L8: 31.2 | M8: 0.005 | N8: 88 | O8: 62
A9: SEC-007 | B9: Fixed Income | C9: Corporate | D9: US | E9: 100000 | F9: 102000 | G9: =E9/SUM($E$3:$E$22) | H9: 0.02 | I9: 0.054 | J9: 0.25 | K9: 0.31 | L9: - | M9: 0.045 | N9: 106 | O9: 99
A10: SEC-008 | B10: Equity | C10: Technology | D10: Intl | E10: 55000 | F10: 67100 | G10: =E10/SUM($E$3:$E$22) | H10: 0.22 | I10: 0.241 | J10: 1.45 | K10: 0.76 | L10: 35.8 | M10: 0.003 | N10: 78 | O10: 48
A11: SEC-009 | B11: Real Estate | C11: REIT | D11: US | E11: 85000 | F11: 88400 | G11: =E11/SUM($E$3:$E$22) | H11: 0.04 | I11: 0.126 | J11: 0.62 | K11: 0.55 | L11: 18.9 | M11: 0.042 | N11: 96 | O11: 78
A12: SEC-010 | B12: Equity | C12: Industrials | D12: US | E12: 65000 | F12: 70200 | G12: =E12/SUM($E$3:$E$22) | H12: 0.08 | I12: 0.153 | J12: 0.92 | K12: 0.84 | L12: 20.4 | M12: 0.018 | N12: 76 | O12: 58
A13: SEC-011 | B13: Commodity | C13: Precious Metals | D13: Global | E13: 40000 | F13: 46000 | G13: =E13/SUM($E$3:$E$22) | H13: 0.15 | I13: 0.228 | J13: 0.38 | K13: 0.22 | L13: - | M13: - | N13: 52 | O13: 36
A14: SEC-012 | B14: Equity | C14: Energy | D14: US | E14: 50000 | F14: 44500 | G14: =E14/SUM($E$3:$E$22) | H14: -0.11 | I14: 0.269 | J14: 0.88 | K14: 0.68 | L14: 12.1 | M14: 0.038 | N14: 62 | O14: 40
A15: SEC-013 | B15: Fixed Income | C15: Municipal | D15: US | E15: 75000 | F15: 76500 | G15: =E15/SUM($E$3:$E$22) | H15: 0.02 | I15: 0.028 | J15: 0.08 | K15: 0.12 | L15: - | M15: 0.029 | N15: 78 | O15: 74
A16: SEC-014 | B16: Equity | C16: Materials | D16: US | E16: 45000 | F16: 49500 | G16: =E16/SUM($E$3:$E$22) | H16: 0.1 | I16: 0.174 | J16: 0.98 | K16: 0.77 | L16: 17.8 | M16: 0.022 | N16: 56 | O16: 42
A17: SEC-015 | B17: Equity | C17: Utilities | D17: US | E17: 55000 | F17: 57750 | G17: =E17/SUM($E$3:$E$22) | H17: 0.05 | I17: 0.102 | J17: 0.44 | K17: 0.52 | L17: 21.3 | M17: 0.035 | N17: 62 | O17: 51
A18: SEC-016 | B18: Equity | C18: Technology | D18: US | E18: 95000 | F18: 118750 | G18: =E18/SUM($E$3:$E$22) | H18: 0.25 | I18: 0.302 | J18: 1.68 | K18: 0.85 | L18: 42.5 | M18: 0.002 | N18: 130 | O18: 80
A19: SEC-017 | B19: Fixed Income | C19: Government | D19: Intl | E19: 70000 | F19: 70700 | G19: =E19/SUM($E$3:$E$22) | H19: 0.01 | I19: 0.042 | J19: 0.15 | K19: 0.2 | L19: - | M19: 0.021 | N19: 73 | O19: 68
A20: SEC-018 | B20: Equity | C20: Consumer Staples | D20: US | E20: 80000 | F20: 84000 | G20: =E20/SUM($E$3:$E$22) | H20: 0.05 | I20: 0.098 | J20: 0.55 | K20: 0.63 | L20: 24.6 | M20: 0.028 | N20: 90 | O20: 76
A21: SEC-019 | B21: Equity | C21: Healthcare | D21: Intl | E21: 60000 | F21: 65400 | G21: =E21/SUM($E$3:$E$22) | H21: 0.09 | I21: 0.165 | J21: 0.82 | K21: 0.69 | L21: 26.8 | M21: 0.016 | N21: 72 | O21: 54
A22: SEC-020 | B22: Commodity | C22: Agriculture | D22: Global | E22: 35000 | F22: 36750 | G22: =E22/SUM($E$3:$E$22) | H22: 0.05 | I22: 0.201 | J22: 0.42 | K22: 0.3 | L22: - | M22: - | N22: 42 | O22: 30
A23: TOTAL PORTFOLIO | E23: =SUM(E3:E22) | F23: =SUM(F3:F22) | G23: =SUM(G3:G22)

Sheet 📈 KPI Engine
A1: KPI ENGINE — PORTFOLIO PERFORMANCE ANALYTICS
A2: ▶ PORTFOLIO LEVEL KPIs
A4: Total Initial Value ($mm) | B4: =$'📊 Raw Data'.E23/1000000
A5: Total Current Value ($mm) | B5: =$'📊 Raw Data'.F23/1000000
A6: Absolute P&L ($mm) | B6: =B5-B4
A7: Portfolio Return (%) | B7: =(B5-B4)/B4
A8: Weighted Avg Volatility | B8: =SUMPRODUCT($'📊 Raw Data'.G3:G22,$'📊 Raw Data'.I3:I22)
A9: Weighted Avg Beta | B9: =SUMPRODUCT($'📊 Raw Data'.G3:G22,$'📊 Raw Data'.J3:J22)
A10: No. of Securities | B10: =COUNTA($'📊 Raw Data'.A3:A22)
A11: Asset Classes | B11: =SUMPRODUCT(1/COUNTIF($'📊 Raw Data'.B3:B22,$'📊 Raw Data'.B3:B22))
A12: Sharpe Ratio (est.) | B12: =(B7/B8)/B8
A13: Portfolio Diversification Score | B13: =1-SUMPRODUCT($'📊 Raw Data'.G3:G22^2)
A15: ▶ ASSET CLASS BREAKDOWN
A16: Asset Class | B16: Count | C16: Total Value ($) | D16: Allocation (%) | E16: Avg Return | F16: Avg Volatility
A17: Equity | B17: =COUNTIF('📊 Raw Data'!B3:B22,A17) | C17: =SUMIF('📊 Raw Data'!B3:B22,A17,'📊 Raw Data'!F3:F22) | D17: =C17/$'📊 Raw Data'.F23 | E17: =AVERAGEIF('📊 Raw Data'!B3:B22,A17,'📊 Raw Data'!H3:H22) | F17: =AVERAGEIF('📊 Raw Data'!B3:B22,A17,'📊 Raw Data'!I3:I22)
A18: Fixed Income | B18: =COUNTIF('📊 Raw Data'!B3:B22,A18) | C18: =SUMIF('📊 Raw Data'!B3:B22,A18,'📊 Raw Data'!F3:F22) | D18: =C18/$'📊 Raw Data'.F23 | E18: =AVERAGEIF('📊 Raw Data'!B3:B22,A18,'📊 Raw Data'!H3:H22) | F18: =AVERAGEIF('📊 Raw Data'!B3:B22,A18,'📊 Raw Data'!I3:I22)
A19: Commodity | B19: =COUNTIF('📊 Raw Data'!B3:B22,A19) | C19: =SUMIF('📊 Raw Data'!B3:B22,A19,'📊 Raw Data'!F3:F22) | D19: =C19/$'📊 Raw Data'.F23 | E19: =AVERAGEIF('📊 Raw Data'!B3:B22,A19,'📊 Raw Data'!H3:H22) | F19: =AVERAGEIF('📊 Raw Data'!B3:B22,A19,'📊 Raw Data'!I3:I22)
A20: Real Estate | B20: =COUNTIF('📊 Raw Data'!B3:B22,A20) | C20: =SUMIF('📊 Raw Data'!B3:B22,A20,'📊 Raw Data'!F3:F22) | D20: =C20/$'📊 Raw Data'.F23 | E20: =AVERAGEIF('📊 Raw Data'!B3:B22,A20,'📊 Raw Data'!H3:H22) | F20: =AVERAGEIF('📊 Raw Data'!B3:B22,A20,'📊 Raw Data'!I3:I22)

Sheet 🎯 Scenario Stress-Test
A1: SCENARIO STRESS-TEST — 5 MARKET SHOCK SCENARIOS
A3: ▶ SCENARIO SHOCK ASSUMPTIONS (Edit Blue Cells)
A4: Scenario | B4: Equity Shock | C4: Bond Shock | D4: Commodity Shock | E4: RE Shock | F4: Vol Multiplier | G4: Beta Amplifier
A5: S1 — Rate Hike (+200bps) | B5: -0.08 | C5: 0.04 | D5: -0.05 | E5: -0.12 | F5: 1.3 | G5: 1.1
A6: S2 — Liquidity Crunch | B6: -0.18 | C6: -0.06 | D6: -0.15 | E6: -0.22 | F6: 2.1 | G6: 1.4
A7: S3 — Equity Market Crash | B7: -0.35 | C7: 0.08 | D7: -0.1 | E7: -0.28 | F7: 3.2 | G7: 1.8
A8: S4 — Currency Devaluation | B8: -0.12 | C8: -0.03 | D8: 0.12 | E8: -0.08 | F8: 1.6 | G8: 1.2
A9: S5 — Stagflation | B9: -0.22 | C9: -0.05 | D9: 0.18 | E9: -0.15 | F9: 2.4 | G9: 1.5
A12: ▶ STRESS-TEST RESULTS — Portfolio P&L Impact
A13: Scenario | B13: Equity P&L ($) | C13: Fixed Inc P&L ($) | D13: Commodity P&L ($) | E13: Real Estate P&L ($) | F13: Total Shock P&L ($) | G13: Portfolio Value After ($) | H13: % Drawdown | I13: Recovery Flag
A14: S1 — Rate Hike (+200bps) | B14: =SUMIF('📊 Raw Data'!B3:B22,"Equity",'📊 Raw Data'!F3:F22)*B5 | C14: =SUMIF('📊 Raw Data'!B3:B22,"Fixed Income",'📊 Raw Data'!F3:F22)*C5 | D14: =SUMIF('📊 Raw Data'!B3:B22,"Commodity",'📊 Raw Data'!F3:F22)*D5 | E14: =SUMIF('📊 Raw Data'!B3:B22,"Real Estate",'📊 Raw Data'!F3:F22)*E5 | F14: =SUM(B14:E14) | G14: ='📊 Raw Data'!F23+F14 | H14: =F14/'📊 Raw Data'!F23 | I14: =IF(G14/'📊 Raw Data'!F23>0.85,"⚠ CRITICAL",IF(G14/'📊 Raw Data'!F23>0.90,"⚡ SEVERE","✅ TOLERABLE"))
A15: S2 — Liquidity Crunch | B15: =SUMIF('📊 Raw Data'!B3:B22,"Equity",'📊 Raw Data'!F3:F22)*B6 | C15: =SUMIF('📊 Raw Data'!B3:B22,"Fixed Income",'📊 Raw Data'!F3:F22)*C6 | D15: =SUMIF('📊 Raw Data'!B3:B22,"Commodity",'📊 Raw Data'!F3:F22)*D6 | E15: =SUMIF('📊 Raw Data'!B3:B22,"Real Estate",'📊 Raw Data'!F3:F22)*E6 | F15: =SUM(B15:E15) | G15: ='📊 Raw Data'!F23+F15 | H15: =F15/'📊 Raw Data'!F23 | I15: =IF(G15/'📊 Raw Data'!F23>0.85,"⚠ CRITICAL",IF(G15/'📊 Raw Data'!F23>0.90,"⚡ SEVERE","✅ TOLERABLE"))
A16: S3 — Equity Market Crash | B16: =SUMIF('📊 Raw Data'!B3:B22,"Equity",'📊 Raw Data'!F3:F22)*B7 | C16: =SUMIF('📊 Raw Data'!B3:B22,"Fixed Income",'📊 Raw Data'!F3:F22)*C7 | D16: =SUMIF('📊 Raw Data'!B3:B22,"Commodity",'📊 Raw Data'!F3:F22)*D7 | E16: =SUMIF('📊 Raw Data'!B3:B22,"Real Estate",'📊 Raw Data'!F3:F22)*E7 | F16: =SUM(B16:E16) | G16: ='📊 Raw Data'!F23+F16 | H16: =F16/'📊 Raw Data'!F23 | I16: =IF(G16/'📊 Raw Data'!F23>0.85,"⚠ CRITICAL",IF(G16/'📊 Raw Data'!F23>0.90,"⚡ SEVERE","✅ TOLERABLE"))
A17: S4 — Currency Devaluation | B17: =SUMIF('📊 Raw Data'!B3:B22,"Equity",'📊 Raw Data'!F3:F22)*B8 | C17: =SUMIF('📊 Raw Data'!B3:B22,"Fixed Income",'📊 Raw Data'!F3:F22)*C8 | D17: =SUMIF('📊 Raw Data'!B3:B22,"Commodity",'📊 Raw Data'!F3:F22)*D8 | E17: =SUMIF('📊 Raw Data'!B3:B22,"Real Estate",'📊 Raw Data'!F3:F22)*E8 | F17: =SUM(B17:E17) | G17: ='📊 Raw Data'!F23+F17 | H17: =F17/'📊 Raw Data'!F23 | I17: =IF(G17/'📊 Raw Data'!F23>0.85,"⚠ CRITICAL",IF(G17/'📊 Raw Data'!F23>0.90,"⚡ SEVERE","✅ TOLERABLE"))
A18: S5 — Stagflation | B18: =SUMIF('📊 Raw Data'!B3:B22,"Equity",'📊 Raw Data'!F3:F22)*B9 | C18: =SUMIF('📊 Raw Data'!B3:B22,"Fixed Income",'📊 Raw Data'!F3:F22)*C9 | D18: =SUMIF('📊 Raw Data'!B3:B22,"Commodity",'📊 Raw Data'!F3:F22)*D9 | E18: =SUMIF('📊 Raw Data'!B3:B22,"Real Estate",'📊 Raw Data'!F3:F22)*E9 | F18: =SUM(B18:E18) | G18: ='📊 Raw Data'!F23+F18 | H18: =F18/'📊 Raw Data'!F23 | I18: =IF(G18/'📊 Raw Data'!F23>0.85,"⚠ CRITICAL",IF(G18/'📊 Raw Data'!F23>0.90,"⚡ SEVERE","✅ TOLERABLE"))

Sheet 📉 VaR Model
A1: VALUE AT RISK (VaR) MODEL — HISTORICAL & PARAMETRIC
A3: ▶ VaR ASSUMPTIONS (Blue = User Input)
A4: Confidence Level | B4: 0.95
A5: Time Horizon (Days) | B5: 10
A6: Risk-Free Rate (Annual) | B6: 0.045
A7: Trading Days per Year | B7: 252
A8: Monte Carlo Simulations | B8: 10000
A10: ▶ VaR CALCULATIONS
A11: Portfolio Std Dev (Daily) | B11: =SUMPRODUCT('📊 Raw Data'!G3:G22,'📊 Raw Data'!I3:I22)/SQRT('📈 KPI Engine'!B10)
A12: Portfolio Std Dev (10-Day) | B12: =B11*SQRT(B5)
A13: Z-Score at Confidence Level | B13: =NORM.INV(B4,0,1)*-1
A14: Parametric VaR (1-Day, $) | B14: ='📊 Raw Data'!F23*B11*B13
A15: Parametric VaR (10-Day, $) | B15: ='📊 Raw Data'!F23*B12*B13
A16: VaR as % of Portfolio | B16: =B15/'📊 Raw Data'!F23
A17: Expected Shortfall (CVaR) | B17: =B15*1.25
A18: Maximum Drawdown (Simulated) | B18: =B15*B7*1.5/B6
A21: ▶ MONTE CARLO SIMULATION — SAMPLE PATHS (30 of 10,000)
A22: Sim # | B22: Day 1 ($) | C22: Day 2 ($) | D22: Day 3 ($) | E22: Day 5 ($) | F22: Day 7 ($) | G22: Day 10 ($) | H22: Min Value ($) | I22: Max Value ($) | J22: P&L ($) | K22: VaR Breach?
A23: 1 | B23: 1043606 | C23: 1041754 | D23: 1040675 | E23: 1048462 | F23: 1034354 | G23: 1030710 | H23: =MIN(B23:G23) | I23: =MAX(B23:G23) | J23: =G23-B23 | K23: =IF(J23<-$B$15,"⚠ BREACH","✅ OK")
A24: 2 | B24: 1048327 | C24: 1063279 | D24: 1071976 | E24: 1064528 | F24: 1055311 | G24: 1072042 | H24: =MIN(B24:G24) | I24: =MAX(B24:G24) | J24: =G24-B24 | K24: =IF(J24<-$B$15,"⚠ BREACH","✅ OK")
A25: 3 | B25: 1052083 | C25: 1034048 | D25: 1030483 | E25: 1048034 | F25: 1050360 | G25: 1050118 | H25: =MIN(B25:G25) | I25: =MAX(B25:G25) | J25: =G25-B25 | K25: =IF(J25<-$B$15,"⚠ BREACH","✅ OK")
A26: 4 | B26: 1052540 | C26: 1033727 | D26: 1001537 | E26: 983913 | F26: 1002777 | G26: 987043 | H26: =MIN(B26:G26) | I26: =MAX(B26:G26) | J26: =G26-B26 | K26: =IF(J26<-$B$15,"⚠ BREACH","✅ OK")
A27: 5 | B27: 1044332 | C27: 1040962 | D27: 1042704 | E27: 1061645 | F27: 1075058 | G27: 1064819 | H27: =MIN(B27:G27) | I27: =MAX(B27:G27) | J27: =G27-B27 | K27: =IF(J27<-$B$15,"⚠ BREACH","✅ OK")
A28: 6 | B28: 1039520 | C28: 1046061 | D28: 1043235 | E28: 1062564 | F28: 1058858 | G28: 1095301 | H28: =MIN(B28:G28) | I28: =MAX(B28:G28) | J28: =G28-B28 | K28: =IF(J28<-$B$15,"⚠ BREACH","✅ OK")
A29: 7 | B29: 1063302 | C29: 1062421 | D29: 1044598 | E29: 1050426 | F29: 1033268 | G29: 1042384 | H29: =MIN(B29:G29) | I29: =MAX(B29:G29) | J29: =G29-B29 | K29: =IF(J29<-$B$15,"⚠ BREACH","✅ OK")
A30: 8 | B30: 1052697 | C30: 1082338 | D30: 1090715 | E30: 1076089 | F30: 1078171 | G30: 1080526 | H30: =MIN(B30:G30) | I30: =MAX(B30:G30) | J30: =G30-B30 | K30: =IF(J30<-$B$15,"⚠ BREACH","✅ OK")
A31: 9 | B31: 1036340 | C31: 1032999 | D31: 1010484 | E31: 991163 | F31: 1010974 | G31: 1016876 | H31: =MIN(B31:G31) | I31: =MAX(B31:G31) | J31: =G31-B31 | K31: =IF(J31<-$B$15,"⚠ BREACH","✅ OK")
A32: 10 | B32: 1059017 | C32: 1070688 | D32: 1074526 | E32: 1073642 | F32: 1095081 | G32: 1116519 | H32: =MIN(B32:G32) | I32: =MAX(B32:G32) | J32: =G32-B32 | K32: =IF(J32<-$B$15,"⚠ BREACH","✅ OK")
A33: 11 | B33: 1065392 | C33: 1067183 | D33: 1060892 | E33: 1045261 | F33: 1074164 | G33: 1062102 | H33: =MIN(B33:G33) | I33: =MAX(B33:G33) | J33: =G33-B33 | K33: =IF(J33<-$B$15,"⚠ BREACH","✅ OK")
A34: 12 | B34: 1052385 | C34: 1045756 | D34: 1038197 | E34: 1060287 | F34: 1042119 | G34: 1049816 | H34: =MIN(B34:G34) | I34: =MAX(B34:G34) | J34: =G34-B34 | K34: =IF(J34<-$B$15,"⚠ BREACH","✅ OK")
... A52: 30 | B52: 1066945 | C52: 1067755 | D52: 1061571 | E52: 1053789 | F52: 1036863 | G52: 1073555 | H52: =MIN(B52:G52) | I52: =MAX(B52:G52) | J52: =G52-B52 | K52: =IF(J52<-$B$15,"⚠ BREACH","✅ OK")

Sheet 🔍 Assumptions
A1: MODEL ASSUMPTIONS & DOCUMENTATION
A2: Parameter | B2: Value | C2: Type | D2: Source | E2: Last Updated | F2: Notes
A3: Risk-Free Rate | B3: 4.50% | C3: Input | D3: US 10Y Treasury Yield | E3: Apr 2026 | F3: Federal Reserve H.15 Release
A4: Market Benchmark | B4: S&P 500 | C4: Input | D4: Bloomberg Terminal | E4: Apr 2026 | F4: Used for Beta & Correlation calc
A5: VaR Confidence Level | B5: 95% | C5: Input | D5: Basel III Standard | E5: Apr 2026 | F5: Industry standard for trading books
A6: Time Horizon | B6: 10 Days | C6: Input | D6: Basel III Standard | E6: Apr 2026 | F6: Regulatory minimum for market risk
A7: Monte Carlo Paths | B7: 10,000 | C7: Input | D7: Industry Standard | E7: Apr 2026 | F7: Balance between accuracy and speed
A8: Daily Volatility Proxy | B8: Annualized ÷ √252 | C8: Formula | D8: Statistical | E8: Apr 2026 | F8: Square root of time rule applied
A9: CVaR Multiplier | B9: 1.25x VaR | C9: Assumption | D9: Empirical | E9: Apr 2026 | F9: Fat-tail adjustment for non-normality
A10: Portfolio Pricing | B10: Mark-to-Market | C10: Convention | D10: IFRS 13 | E10: Apr 2026 | F10: Fair value hierarchy Level 1 assets
A11: Correlation Matrix | B11: Pairwise SPX | C11: Simplification | D11: Bloomberg | E11: Apr 2026 | F11: Full correlation matrix in v2.0
A12: Dividend Reinvestment | B12: Not assumed | C12: Convention | D12: Internal | E12: Apr 2026 | F12: Total return basis for returns
A13: Tax Treatment | B13: Pre-tax | C13: Convention | D13: Internal | E13: Apr 2026 | F13: Gross returns only
A14: Rebalancing Frequency | B14: Monthly | C14: Assumption | D14: Internal | E14: Apr 2026 | F14: Portfolio weights reset monthly
